{"updateTime":"2024-01-18 02:19:52","data":[{"full_name":"","description":"A fast and lightweight tool for querying and manipulating SQLCE databases. This tool supports SQLCE versions 3.0, 3.1, 3.5 and 4.0","currentPeriodStars":2,"language":"ANTLR","languageColor":"#9DC3FF","stargazers_count":49,"forks_count":0,"owner":{"avatar_url":"https://avatars.githubusercontent.com/u/710400?s=40&v=4","login":"christianhelle"},"buildBy":[{"avatar_url":"https://avatars.githubusercontent.com/u/710400?s=40&v=4","login":"christianhelle"},{"avatar_url":"https://avatars.githubusercontent.com/u/5789496?s=40&v=4","login":"diotteo"},{"avatar_url":"https://avatars.githubusercontent.com/in/2740?s=40&v=4","login":"renovate"},{"avatar_url":"https://avatars.githubusercontent.com/in/29110?s=40&v=4","login":"dependabot"},{"avatar_url":"https://avatars.githubusercontent.com/u/765343?s=40&v=4","login":"greenozon"}]}]}