{"updateTime":"2022-12-23 02:21:51","data":[{"username":"MichaIng","name":"MichaIng","type":"user","url":"https://github.com/MichaIng","avatar":"https://avatars.githubusercontent.com/u/28480705?s=96&v=4","repo":{"name":"DietPi","description":"Lightweight justice for your single-board computer!","url":"https://github.com/MichaIng/DietPi"}},{"username":"vitkarpov","name":"Viktor Karpov","type":"user","url":"https://github.com/vitkarpov","avatar":"https://avatars.githubusercontent.com/u/3001791?s=96&v=4","repo":{"name":"coding-interviews-blog-archive","description":"vitkarpov.me blog archive","url":"https://github.com/vitkarpov/coding-interviews-blog-archive"}},{"username":"JamesHenry","name":"James Henry","type":"user","url":"https://github.com/JamesHenry","avatar":"https://avatars.githubusercontent.com/u/900523?s=96&v=4","repo":{"name":"parallel-bash-commands","description":"✨ A Github Action which executes a list of bash commands in parallel and waits for them all to successfully complete","url":"https://github.com/JamesHenry/parallel-bash-commands"}},{"username":"igorpecovnik","name":"Igor Pečovnik","type":"user","url":"https://github.com/igorpecovnik","avatar":"https://avatars.githubusercontent.com/u/6281704?s=96&v=4","repo":{"name":"BananaPI-Debian","description":"Scripts to create an Image of Debian for Banana PI","url":"https://github.com/igorpecovnik/BananaPI-Debian"}},{"username":"charlax","name":"Charles-Axel Dein","type":"user","url":"https://github.com/charlax","avatar":"https://avatars.githubusercontent.com/u/120501?s=96&v=4","repo":{"name":"engineering-management","description":"A collection of inspiring resources related to engineering management and tech leadership","url":"https://github.com/charlax/engineering-management"}},{"username":"th33xitus","name":"th33xitus","type":"user","url":"https://github.com/th33xitus","avatar":"https://avatars.githubusercontent.com/u/31533186?s=96&v=4","repo":{"name":"kiauh","description":"Klipper Installation And Update Helper","url":"https://github.com/th33xitus/kiauh"}},{"username":"biodranik","name":"Alexander Borsuk","type":"user","url":"https://github.com/biodranik","avatar":"https://avatars.githubusercontent.com/u/170263?s=96&v=4","repo":{"name":"sd-card-speed-test","description":"Bash script for Mac OS X and Linux to test SD card or SSD/HDD read and write speed.","url":"https://github.com/biodranik/sd-card-speed-test"}},{"username":"ornicar","name":"Thibault Duplessis","type":"user","url":"https://github.com/ornicar","avatar":"https://avatars.githubusercontent.com/u/140370?s=96&v=4","repo":{"name":"dotfiles","description":"My beloved Linux dot files for zsh, tmux, git, tig, vim, mpd, mutt, rtorrent, weechat, xmonad, urxvt, vimperator, ranger...","url":"https://github.com/ornicar/dotfiles"}},{"username":"allenporter","name":"Allen Porter","type":"user","url":"https://github.com/allenporter","avatar":"https://avatars.githubusercontent.com/u/6026418?s=96&v=4","repo":{"name":"k8s-gitops","description":"Flux/Gitops managed k8s cluster","url":"https://github.com/allenporter/k8s-gitops"}},{"username":"deviantony","name":"Anthony Lapenna","type":"user","url":"https://github.com/deviantony","avatar":"https://avatars.githubusercontent.com/u/5485061?s=96&v=4","repo":{"name":"docker-elk","description":"The Elastic stack (ELK) powered by Docker and Compose.","url":"https://github.com/deviantony/docker-elk"}},{"username":"mislav","name":"Mislav Marohnić","type":"user","url":"https://github.com/mislav","avatar":"https://avatars.githubusercontent.com/u/887?s=96&v=4","repo":{"name":"dotfiles","description":"bash, zsh, git, tmux, personal toolbox","url":"https://github.com/mislav/dotfiles"}},{"username":"bartoszmajsak","name":"Bartosz Majsak","type":"user","url":"https://github.com/bartoszmajsak","avatar":"https://avatars.githubusercontent.com/u/719616?s=96&v=4","repo":{"name":"asdf-oc","description":"OpenShift Client Tools plugin for asdf version manager","url":"https://github.com/bartoszmajsak/asdf-oc"}},{"username":"overvenus","name":"Neil Shen","type":"user","url":"https://github.com/overvenus","avatar":"https://avatars.githubusercontent.com/u/2150711?s=96&v=4","repo":{"name":"tc-script","description":"","url":"https://github.com/overvenus/tc-script"}},{"username":"Anduin2017","name":"Anduin Xue","type":"user","url":"https://github.com/Anduin2017","avatar":"https://avatars.githubusercontent.com/u/19531547?s=96&v=4","repo":{"name":"HowToCook","description":"程序员在家做饭方法指南。Programmer's guide about how to cook at home (Chinese only).","url":"https://github.com/Anduin2017/HowToCook"}},{"username":"angristan","name":"Stanislas","type":"user","url":"https://github.com/angristan","avatar":"https://avatars.githubusercontent.com/u/11699655?s=96&v=4","repo":{"name":"openvpn-install","description":"Set up your own OpenVPN server on Debian, Ubuntu, Fedora, CentOS or Arch Linux.","url":"https://github.com/angristan/openvpn-install"}},{"username":"jparrill","name":"Juan Manuel Parrilla Madrid","type":"user","url":"https://github.com/jparrill","avatar":"https://avatars.githubusercontent.com/u/1569950?s=96&v=4","repo":{"name":"ztp-the-hard-way","description":"Zero Touch Provisioning in the hard way","url":"https://github.com/jparrill/ztp-the-hard-way"}},{"username":"l0b0","name":"Victor Engmark","type":"user","url":"https://github.com/l0b0","avatar":"https://avatars.githubusercontent.com/u/168301?s=96&v=4","repo":{"name":"tilde","description":"Linux home directory configuration and utilities","url":"https://github.com/l0b0/tilde"}},{"username":"grahampugh","name":"Graham Pugh","type":"user","url":"https://github.com/grahampugh","avatar":"https://avatars.githubusercontent.com/u/5802725?s=96&v=4","repo":{"name":"erase-install","description":"A script that automates downloading macOS installers, and optionally erasing or upgrading macOS in a single process.","url":"https://github.com/grahampugh/erase-install"}},{"username":"dylanaraps","name":"dylan","type":"user","url":"https://github.com/dylanaraps","avatar":"https://avatars.githubusercontent.com/u/6799467?s=96&v=4","repo":{"name":"neofetch","description":"🖼️ A command-line system information tool written in bash 3.2+","url":"https://github.com/dylanaraps/neofetch"}},{"username":"kylef","name":"Kyle Fuller","type":"user","url":"https://github.com/kylef","avatar":"https://avatars.githubusercontent.com/u/44164?s=96&v=4","repo":{"name":"swiftenv","description":"Swift Version Manager","url":"https://github.com/kylef/swiftenv"}},{"username":"freekmurze","name":"Freek Van der Herten","type":"user","url":"https://github.com/freekmurze","avatar":"https://avatars.githubusercontent.com/u/483853?s=96&v=4","repo":{"name":"dotfiles","description":"My personal dotfiles","url":"https://github.com/freekmurze/dotfiles"}},{"username":"xmonader","name":"xmonader","type":"user","url":"https://github.com/xmonader","avatar":"https://avatars.githubusercontent.com/u/64129?s=96&v=4","repo":{"name":"nimdays","description":"Nim days book","url":"https://github.com/xmonader/nimdays"}},{"username":"jnsgruk","name":"Jon Seager","type":"user","url":"https://github.com/jnsgruk","avatar":"https://avatars.githubusercontent.com/u/668505?s=96&v=4","repo":{"name":"wireguard-over-wss","description":"Resources to tunnel Wireguard over Websockets","url":"https://github.com/jnsgruk/wireguard-over-wss"}},{"username":"sergeysova","name":"Sergey Sova","type":"user","url":"https://github.com/sergeysova","avatar":"https://avatars.githubusercontent.com/u/5620073?s=96&v=4","repo":{"name":"jq-action","description":"This lets you do jq operations in GitHub Actions.","url":"https://github.com/sergeysova/jq-action"}}]}