{"updateTime":"2025-06-13 02:30:59","data":[{"username":"davepl","name":"David W Plummer        ","type":"user","url":"https://github.com/davepl","avatar":"https://avatars.githubusercontent.com/u/3698967?s=96&v=4","repo":{"name":"tempest_ai","description":"","url":"https://github.com/davepl/tempest_ai"}},{"username":"lukechampine","name":"Luke Champine        ","type":"user","url":"https://github.com/lukechampine","avatar":"https://avatars.githubusercontent.com/u/3344749?s=96&v=4","repo":{"name":"blake3","description":"An AVX-512 accelerated implementation of the BLAKE3 cryptographic hash function","url":"https://github.com/lukechampine/blake3"}},{"username":"briansmith","name":"Brian Smith        ","type":"user","url":"https://github.com/briansmith","avatar":"https://avatars.githubusercontent.com/u/16816?s=96&v=4","repo":{"name":"ring","description":"An experiment.","url":"https://github.com/briansmith/ring"}},{"username":"mschwartz","name":"Michael Schwartz        ","type":"user","url":"https://github.com/mschwartz","avatar":"https://avatars.githubusercontent.com/u/329637?s=96&v=4","repo":{"name":"assembly-tutorial","description":"Programming in assembly language tutorial","url":"https://github.com/mschwartz/assembly-tutorial"}}]}