{"updateTime":"2023-03-22 02:21:46","data":[{"username":"th33xitus","name":"th33xitus","type":"user","url":"https://github.com/th33xitus","avatar":"https://avatars.githubusercontent.com/u/31533186?s=96&v=4","repo":{"name":"kiauh","description":"Klipper Installation And Update Helper","url":"https://github.com/th33xitus/kiauh"}},{"username":"lloesche","name":"Lukas Lösche","type":"user","url":"https://github.com/lloesche","avatar":"https://avatars.githubusercontent.com/u/2124094?s=96&v=4","repo":{"name":"valheim-server-docker","description":"Valheim dedicated gameserver with automatic update, World backup, BepInEx and ValheimPlus mod support","url":"https://github.com/lloesche/valheim-server-docker"}},{"username":"hagen1778","name":"Roman Khavronenko","type":"user","url":"https://github.com/hagen1778","avatar":"https://avatars.githubusercontent.com/u/2902918?s=96&v=4","repo":{"name":"grafana-import-export","description":"shell scripts for importing and exporting Grafana's dashboards and datasources","url":"https://github.com/hagen1778/grafana-import-export"}},{"username":"shapeshed","name":"George Ornbo","type":"user","url":"https://github.com/shapeshed","avatar":"https://avatars.githubusercontent.com/u/33444?s=96&v=4","repo":{"name":"remarkable-crosswords","description":"Get crosswords freshly delivered to your reMarkable every morning.","url":"https://github.com/shapeshed/remarkable-crosswords"}},{"username":"wfxr","name":"Wenxuan","type":"user","url":"https://github.com/wfxr","avatar":"https://avatars.githubusercontent.com/u/6105425?s=96&v=4","repo":{"name":"forgit","description":"💤 A utility tool powered by fzf for using git interactively.","url":"https://github.com/wfxr/forgit"}},{"username":"angristan","name":"Stanislas","type":"user","url":"https://github.com/angristan","avatar":"https://avatars.githubusercontent.com/u/11699655?s=96&v=4","repo":{"name":"wireguard-install","description":"WireGuard VPN installer for Linux servers","url":"https://github.com/angristan/wireguard-install"}},{"username":"tamalsaha","name":"Tamal Saha","type":"user","url":"https://github.com/tamalsaha","avatar":"https://avatars.githubusercontent.com/u/94814?s=96&v=4","repo":{"name":"cloud-hypervisor-go-client","description":"","url":"https://github.com/tamalsaha/cloud-hypervisor-go-client"}},{"username":"jsturtevant","name":"James Sturtevant","type":"user","url":"https://github.com/jsturtevant","avatar":"https://avatars.githubusercontent.com/u/648372?s=96&v=4","repo":{"name":"dotfiles","description":"","url":"https://github.com/jsturtevant/dotfiles"}},{"username":"na--","name":"na--","type":"user","url":"https://github.com/na--","avatar":"https://avatars.githubusercontent.com/u/3336773?s=96&v=4","repo":{"name":"ebook-tools","description":"Shell scripts for organizing and managing ebook collections","url":"https://github.com/na--/ebook-tools"}},{"username":"frozzare","name":"Fredrik Forsmo","type":"user","url":"https://github.com/frozzare","avatar":"https://avatars.githubusercontent.com/u/14610?s=96&v=4","repo":{"name":"dotfiles","description":"My dotfiles","url":"https://github.com/frozzare/dotfiles"}},{"username":"jnsgruk","name":"Jon Seager","type":"user","url":"https://github.com/jnsgruk","avatar":"https://avatars.githubusercontent.com/u/668505?s=96&v=4","repo":{"name":"wireguard-over-wss","description":"Resources to tunnel Wireguard over Websockets","url":"https://github.com/jnsgruk/wireguard-over-wss"}},{"username":"dylanaraps","name":"dylan","type":"user","url":"https://github.com/dylanaraps","avatar":"https://avatars.githubusercontent.com/u/6799467?s=96&v=4","repo":{"name":"neofetch","description":"🖼️ A command-line system information tool written in bash 3.2+","url":"https://github.com/dylanaraps/neofetch"}},{"username":"batrick","name":"Patrick Donnelly","type":"user","url":"https://github.com/batrick","avatar":"https://avatars.githubusercontent.com/u/548304?s=96&v=4","repo":{"name":"ceph-linode","description":"Launch Ceph using the Linode VPS provider","url":"https://github.com/batrick/ceph-linode"}},{"username":"nodiscc","name":"nodiscc","type":"user","url":"https://github.com/nodiscc","avatar":"https://avatars.githubusercontent.com/u/3950390?s=96&v=4","repo":{"name":"awesome-linuxaudio","description":"[mirror] A list of software and resources for professional audio/video/live events production on Linux.","url":"https://github.com/nodiscc/awesome-linuxaudio"}},{"username":"thomaspaulmann","name":"Thomas Paul Mann","type":"user","url":"https://github.com/thomaspaulmann","avatar":"https://avatars.githubusercontent.com/u/12066405?s=96&v=4","repo":{"name":"Swish","description":"👷Build Swift Projects on a Remote Machine within Xcode.","url":"https://github.com/thomaspaulmann/Swish"}},{"username":"ajsutton","name":"Adrian Sutton","type":"user","url":"https://github.com/ajsutton","avatar":"https://avatars.githubusercontent.com/u/72675?s=96&v=4","repo":{"name":"merge-scripts","description":"Scripts to setup or join testnets for the merge","url":"https://github.com/ajsutton/merge-scripts"}},{"username":"miguelgfierro","name":"Miguel Fierro","type":"user","url":"https://github.com/miguelgfierro","avatar":"https://avatars.githubusercontent.com/u/3491412?s=96&v=4","repo":{"name":"scripts","description":"A collection of useful shell scripts for Linux, Windows & Mac","url":"https://github.com/miguelgfierro/scripts"}},{"username":"bendory","name":"David Bendory","type":"user","url":"https://github.com/bendory","avatar":"https://avatars.githubusercontent.com/u/17419217?s=96&v=4","repo":{"name":"tekton-on-gcp","description":"Script setup of Tekton on GCP, from standup through end-to-end build-and-push of container to AR.","url":"https://github.com/bendory/tekton-on-gcp"}},{"username":"iandunn","name":"Ian Dunn","type":"user","url":"https://github.com/iandunn","avatar":"https://avatars.githubusercontent.com/u/484068?s=96&v=4","repo":{"name":"dotfiles","description":"A central repository to store my personal config/settings for distribution across multiple systems","url":"https://github.com/iandunn/dotfiles"}},{"username":"p","name":"Oleg Pudeyev","type":"user","url":"https://github.com/p","avatar":"https://avatars.githubusercontent.com/u/125612?s=96&v=4","repo":{"name":"adblock","description":"DNS level ad blocking","url":"https://github.com/p/adblock"}},{"username":"deviantony","name":"Anthony Lapenna","type":"user","url":"https://github.com/deviantony","avatar":"https://avatars.githubusercontent.com/u/5485061?s=96&v=4","repo":{"name":"docker-elk","description":"The Elastic stack (ELK) powered by Docker and Compose.","url":"https://github.com/deviantony/docker-elk"}},{"username":"idan","name":"Idan Gazit","type":"user","url":"https://github.com/idan","avatar":"https://avatars.githubusercontent.com/u/22723?s=96&v=4","repo":{"name":"autoenvfish","description":"Directory-based environments for the Fish shell","url":"https://github.com/idan/autoenvfish"}},{"username":"robinmanuelthiel","name":"Robin-Manuel Thiel","type":"user","url":"https://github.com/robinmanuelthiel","avatar":"https://avatars.githubusercontent.com/u/5874465?s=96&v=4","repo":{"name":"speedtest","description":"Check internet bandwidth from a Docker container and save the results to an InfluxDB","url":"https://github.com/robinmanuelthiel/speedtest"}},{"username":"ldodds","name":"Leigh Dodds","type":"user","url":"https://github.com/ldodds","avatar":"https://avatars.githubusercontent.com/u/109082?s=96&v=4","repo":{"name":"scifi-terminals","description":"Recreating terminal windows from scifi movies","url":"https://github.com/ldodds/scifi-terminals"}}]}