{"updateTime":"2023-01-19 02:20:06","data":[{"username":"jomjol","name":"jomjol","type":"user","url":"https://github.com/jomjol","avatar":"https://avatars.githubusercontent.com/u/30766535?s=96&v=4","repo":{"name":"AI-on-the-edge-device","description":"Easy to use device for connecting \"old\" measuring units (water, power, gas, ...) to the digital world","url":"https://github.com/jomjol/AI-on-the-edge-device"}},{"username":"earlephilhower","name":"Earle F. Philhower, III","type":"user","url":"https://github.com/earlephilhower","avatar":"https://avatars.githubusercontent.com/u/11875?s=96&v=4","repo":{"name":"arduino-pico","description":"Raspberry Pi Pico Arduino core, for all RP2040 boards","url":"https://github.com/earlephilhower/arduino-pico"}},{"username":"lstein","name":"Lincoln Stein","type":"user","url":"https://github.com/lstein","avatar":"https://avatars.githubusercontent.com/u/111189?s=96&v=4","repo":{"name":"Net-ISP-Balance","description":"Set of scripts to load-balance your Internet connection across two or more ISPs with auto failover","url":"https://github.com/lstein/Net-ISP-Balance"}},{"username":"stefanberger","name":"Stefan Berger","type":"user","url":"https://github.com/stefanberger","avatar":"https://avatars.githubusercontent.com/u/1873348?s=96&v=4","repo":{"name":"swtpm","description":"Libtpms-based TPM emulator with socket, character device, and Linux CUSE interface.","url":"https://github.com/stefanberger/swtpm"}},{"username":"saghul","name":"Saúl Ibarra Corretgé","type":"user","url":"https://github.com/saghul","avatar":"https://avatars.githubusercontent.com/u/317464?s=96&v=4","repo":{"name":"txiki.js","description":"A tiny JavaScript runtime","url":"https://github.com/saghul/txiki.js"}},{"username":"giuseppe","name":"Giuseppe Scrivano","type":"user","url":"https://github.com/giuseppe","avatar":"https://avatars.githubusercontent.com/u/67430?s=96&v=4","repo":{"name":"become-root","description":"minimal tool for creating a new user namespace with multiple UIDs/GIDs mapped inside","url":"https://github.com/giuseppe/become-root"}},{"username":"Wilfred","name":"Wilfred Hughes","type":"user","url":"https://github.com/Wilfred","avatar":"https://avatars.githubusercontent.com/u/70800?s=96&v=4","repo":{"name":"difftastic","description":"a structural diff that understands syntax 🟥🟩","url":"https://github.com/Wilfred/difftastic"}},{"username":"hathach","name":"Ha Thach","type":"user","url":"https://github.com/hathach","avatar":"https://avatars.githubusercontent.com/u/249515?s=96&v=4","repo":{"name":"tinyusb","description":"An open source cross-platform USB stack for embedded system","url":"https://github.com/hathach/tinyusb"}},{"username":"neonichu","name":"Boris Bügling","type":"user","url":"https://github.com/neonichu","avatar":"https://avatars.githubusercontent.com/u/118992?s=96&v=4","repo":{"name":"trolldrop","description":"AirDrop trollfaces to everyone.","url":"https://github.com/neonichu/trolldrop"}},{"username":"terorie","name":"Richard Patel","type":"user","url":"https://github.com/terorie","avatar":"https://avatars.githubusercontent.com/u/21371810?s=96&v=4","repo":{"name":"mwcc-native","description":"[WIP] CodeWarrior on Linux (PE-to-ELF)","url":"https://github.com/terorie/mwcc-native"}},{"username":"cpq","name":"Sergey Lyubka","type":"user","url":"https://github.com/cpq","avatar":"https://avatars.githubusercontent.com/u/601816?s=96&v=4","repo":{"name":"bare-metal-programming-guide","description":"A bare metal programming guide (ARM microcontrollers)","url":"https://github.com/cpq/bare-metal-programming-guide"}},{"username":"gr455","name":"Ruturaj Mohite","type":"user","url":"https://github.com/gr455","avatar":"https://avatars.githubusercontent.com/u/53974118?s=96&v=4","repo":{"name":"vSOS","description":"Hey vSOS! kernel here","url":"https://github.com/gr455/vSOS"}},{"username":"edenhill","name":"Magnus Edenhill","type":"user","url":"https://github.com/edenhill","avatar":"https://avatars.githubusercontent.com/u/524990?s=96&v=4","repo":{"name":"kcat","description":"Generic command line non-JVM Apache Kafka producer and consumer","url":"https://github.com/edenhill/kcat"}},{"username":"stedolan","name":"Stephen Dolan","type":"user","url":"https://github.com/stedolan","avatar":"https://avatars.githubusercontent.com/u/79765?s=96&v=4","repo":{"name":"jq","description":"Command-line JSON processor","url":"https://github.com/stedolan/jq"}},{"username":"floooh","name":"Andre Weissflog","type":"user","url":"https://github.com/floooh","avatar":"https://avatars.githubusercontent.com/u/1699414?s=96&v=4","repo":{"name":"sokol","description":"minimal cross-platform standalone C headers","url":"https://github.com/floooh/sokol"}},{"username":"Rinnegatamante","name":"Rinnegatamante","type":"user","url":"https://github.com/Rinnegatamante","avatar":"https://avatars.githubusercontent.com/u/9152710?s=96&v=4","repo":{"name":"vitaGL","description":"openGL wrapper for PSVITA.","url":"https://github.com/Rinnegatamante/vitaGL"}},{"username":"dustin","name":"Dustin Sallings","type":"user","url":"https://github.com/dustin","avatar":"https://avatars.githubusercontent.com/u/1779?s=96&v=4","repo":{"name":"memcached","description":"Memcached -- you all use it. Get it here.","url":"https://github.com/dustin/memcached"}},{"username":"jonashaag","name":"Jonas Haag","type":"user","url":"https://github.com/jonashaag","avatar":"https://avatars.githubusercontent.com/u/175722?s=96&v=4","repo":{"name":"bjoern","description":"A screamingly fast Python 2/3 WSGI server written in C.","url":"https://github.com/jonashaag/bjoern"}},{"username":"zone117x","name":"Matthew Little","type":"user","url":"https://github.com/zone117x","avatar":"https://avatars.githubusercontent.com/u/1447546?s=96&v=4","repo":{"name":"node-multi-hashing","description":"","url":"https://github.com/zone117x/node-multi-hashing"}},{"username":"kuba--","name":"Kuba Podgórski","type":"user","url":"https://github.com/kuba--","avatar":"https://avatars.githubusercontent.com/u/4056521?s=96&v=4","repo":{"name":"zip","description":"A portable, simple zip library written in C","url":"https://github.com/kuba--/zip"}},{"username":"shibatch","name":"Naoki Shibata","type":"user","url":"https://github.com/shibatch","avatar":"https://avatars.githubusercontent.com/u/15994775?s=96&v=4","repo":{"name":"sleef","description":"SIMD Library for Evaluating Elementary Functions, vectorized libm and DFT","url":"https://github.com/shibatch/sleef"}},{"username":"SRombauts","name":"Sébastien Rombauts","type":"user","url":"https://github.com/SRombauts","avatar":"https://avatars.githubusercontent.com/u/868490?s=96&v=4","repo":{"name":"SQLiteCpp","description":"SQLiteC++ (SQLiteCpp) is a smart and easy to use C++ SQLite3 wrapper.","url":"https://github.com/SRombauts/SQLiteCpp"}},{"username":"cloudwu","name":"云风","type":"user","url":"https://github.com/cloudwu","avatar":"https://avatars.githubusercontent.com/u/729648?s=96&v=4","repo":{"name":"skynet","description":"A lightweight online game framework","url":"https://github.com/cloudwu/skynet"}},{"username":"CohenArthur","name":"CohenArthur","type":"user","url":"https://github.com/CohenArthur","avatar":"https://avatars.githubusercontent.com/u/43524065?s=96&v=4","repo":{"name":"wren","description":"The Wren Programming Language","url":"https://github.com/CohenArthur/wren"}},{"username":"flori","name":"Florian Frank","type":"user","url":"https://github.com/flori","avatar":"https://avatars.githubusercontent.com/u/15918?s=96&v=4","repo":{"name":"amatch","description":"Approximate String Matching library","url":"https://github.com/flori/amatch"}}]}