{"updateTime":"2025-08-16 02:34:30","data":[{"username":"peterdesmet","name":"Peter Desmet        ","type":"user","url":"https://github.com/peterdesmet","avatar":"https://avatars.githubusercontent.com/u/600993?s=96&v=4","repo":{"name":"petridish","description":"Jekyll theme for research project websites 🧫","url":"https://github.com/peterdesmet/petridish"}},{"username":"fi3ework","name":"Wei        ","type":"user","url":"https://github.com/fi3ework","avatar":"https://avatars.githubusercontent.com/u/12322740?s=96&v=4","repo":{"name":"hexo-theme-archer","description":"🎯 A smart and modern theme for Hexo.","url":"https://github.com/fi3ework/hexo-theme-archer"}}]}