{"updateTime":"2023-10-07 02:21:23","data":[{"username":"stnguyen90","name":"Steven Nguyen","type":"user","url":"https://github.com/stnguyen90","avatar":"https://avatars.githubusercontent.com/u/1477010?s=96&v=4","repo":{"name":"appwrite-console","description":"The Console that makes Appwrite tick from the browser 🖥","url":"https://github.com/stnguyen90/appwrite-console"}},{"username":"stolinski","name":"Scott Tolinski","type":"user","url":"https://github.com/stolinski","avatar":"https://avatars.githubusercontent.com/u/669383?s=96&v=4","repo":{"name":"breathe","description":"A box breathing app made with Svelte Kit. Tracks your breathing via your microphone.","url":"https://github.com/stolinski/breathe"}}]}