{"updateTime":"2023-07-24 02:17:31","data":[{"full_name":"","description":"Smart Activation Script","currentPeriodStars":42,"language":"Batchfile","languageColor":"#C1F12E","stargazers_count":6394,"forks_count":0,"owner":{"avatar_url":"https://avatars.githubusercontent.com/u/33669284?s=40&v=4","login":"abbodi1406"},"buildBy":[{"avatar_url":"https://avatars.githubusercontent.com/u/33669284?s=40&v=4","login":"abbodi1406"}]},{"full_name":"","description":"Medicat Installer Repo","currentPeriodStars":73,"language":"Batchfile","languageColor":"#C1F12E","stargazers_count":558,"forks_count":0,"owner":{"avatar_url":"https://avatars.githubusercontent.com/u/43628254?s=40&v=4","login":"mon5termatt"},"buildBy":[{"avatar_url":"https://avatars.githubusercontent.com/u/43628254?s=40&v=4","login":"mon5termatt"},{"avatar_url":"https://avatars.githubusercontent.com/u/37031361?s=40&v=4","login":"Teknoist"},{"avatar_url":"https://avatars.githubusercontent.com/u/77866043?s=40&v=4","login":"Ben-Hampson"},{"avatar_url":"https://avatars.githubusercontent.com/u/96273359?s=40&v=4","login":"SkeletonMan03"},{"avatar_url":"https://avatars.githubusercontent.com/u/25128554?s=40&v=4","login":"Samega7Cattac"}]},{"full_name":"","description":"a DOTA dashboard mod to bring back the mmr numbers now that rank changes are variable","currentPeriodStars":4,"language":"Batchfile","languageColor":"#C1F12E","stargazers_count":35,"forks_count":0,"owner":{"avatar_url":"https://avatars.githubusercontent.com/u/12874843?s=40&v=4","login":"AveYo"},"buildBy":[{"avatar_url":"https://avatars.githubusercontent.com/u/12874843?s=40&v=4","login":"AveYo"}]},{"full_name":"","description":"查找适合自己当前网络环境的优选cloudflare anycast IP","currentPeriodStars":61,"language":"Batchfile","languageColor":"#C1F12E","stargazers_count":1990,"forks_count":0,"owner":{"avatar_url":"https://avatars.githubusercontent.com/u/26161605?s=40&v=4","login":"badafans"},"buildBy":[{"avatar_url":"https://avatars.githubusercontent.com/u/26161605?s=40&v=4","login":"badafans"}]},{"full_name":"","description":"RCO tweaks FFlags to optimize your Roblox client","currentPeriodStars":10,"language":"Batchfile","languageColor":"#C1F12E","stargazers_count":62,"forks_count":0,"owner":{"avatar_url":"https://avatars.githubusercontent.com/u/49875377?s=40&v=4","login":"L8X"},"buildBy":[{"avatar_url":"https://avatars.githubusercontent.com/u/49875377?s=40&v=4","login":"L8X"}]},{"full_name":"","description":"Вопросы и ответы к интервью Java разработчика","currentPeriodStars":20,"language":"Batchfile","languageColor":"#C1F12E","stargazers_count":4227,"forks_count":0,"owner":{"avatar_url":"https://avatars.githubusercontent.com/u/757085?s=40&v=4","login":"KhArtNJava"},"buildBy":[{"avatar_url":"https://avatars.githubusercontent.com/u/757085?s=40&v=4","login":"KhArtNJava"},{"avatar_url":"https://avatars.githubusercontent.com/u/6253660?s=40&v=4","login":"enhorse"},{"avatar_url":"https://avatars.githubusercontent.com/u/54657539?s=40&v=4","login":"Cupcake-master"},{"avatar_url":"https://avatars.githubusercontent.com/u/4526420?s=40&v=4","login":"lehaSVV2009"},{"avatar_url":"https://avatars.githubusercontent.com/u/5359109?s=40&v=4","login":"andrii-ashomok"}]},{"full_name":"","description":"A Windows and Office activator using HWID / KMS38 / Online KMS activation methods, with a focus on open-source code and fewer antivirus detections.","currentPeriodStars":429,"language":"Batchfile","languageColor":"#C1F12E","stargazers_count":38024,"forks_count":0,"owner":{"avatar_url":"https://avatars.githubusercontent.com/u/40813939?s=40&v=4","login":"WindowsAddict"},"buildBy":[{"avatar_url":"https://avatars.githubusercontent.com/u/40813939?s=40&v=4","login":"WindowsAddict"},{"avatar_url":"https://avatars.githubusercontent.com/u/41545165?s=40&v=4","login":"mspaintmsi"}]},{"full_name":"","description":"LineageOS based firmware for Anbernic Unisoc T618 devices","currentPeriodStars":13,"language":"Batchfile","languageColor":"#C1F12E","stargazers_count":83,"forks_count":0,"owner":{"avatar_url":"https://avatars.githubusercontent.com/u/116582950?s=40&v=4","login":"TheGammaSqueeze"},"buildBy":[{"avatar_url":"https://avatars.githubusercontent.com/u/116582950?s=40&v=4","login":"TheGammaSqueeze"},{"avatar_url":"https://avatars.githubusercontent.com/u/135996455?s=40&v=4","login":"poc-sm"}]},{"full_name":"","description":"A tool which is uses to remove Windows Defender in Windows 8.x, Windows 10 (every version) and Windows 11.","currentPeriodStars":19,"language":"Batchfile","languageColor":"#C1F12E","stargazers_count":765,"forks_count":0,"owner":{"avatar_url":"https://avatars.githubusercontent.com/u/76656855?s=40&v=4","login":"ionuttbara"},"buildBy":[{"avatar_url":"https://avatars.githubusercontent.com/u/76656855?s=40&v=4","login":"ionuttbara"},{"avatar_url":"https://avatars.githubusercontent.com/u/1227781?s=40&v=4","login":"laramy2020"},{"avatar_url":"https://avatars.githubusercontent.com/u/952007?s=40&v=4","login":"szepeviktor"},{"avatar_url":"https://avatars.githubusercontent.com/u/9846948?s=40&v=4","login":"FadeMind"},{"avatar_url":"https://avatars.githubusercontent.com/u/79479952?s=40&v=4","login":"alainQtec"}]},{"full_name":"","description":"IDM Activation & Trail Reset Script","currentPeriodStars":37,"language":"Batchfile","languageColor":"#C1F12E","stargazers_count":618,"forks_count":0,"owner":{"avatar_url":"https://avatars.githubusercontent.com/u/88411318?s=40&v=4","login":"lstprjct"},"buildBy":[{"avatar_url":"https://avatars.githubusercontent.com/u/88411318?s=40&v=4","login":"lstprjct"}]},{"full_name":"","description":"Stable Diffusion Portable","currentPeriodStars":13,"language":"Batchfile","languageColor":"#C1F12E","stargazers_count":390,"forks_count":0,"owner":{"avatar_url":"https://avatars.githubusercontent.com/u/24704153?s=40&v=4","login":"serpotapov"},"buildBy":[{"avatar_url":"https://avatars.githubusercontent.com/u/24704153?s=40&v=4","login":"serpotapov"},{"avatar_url":"https://avatars.githubusercontent.com/u/1196046?s=40&v=4","login":"XpucT"}]},{"full_name":"","description":"Windows sandbox 腾讯全家桶沙盒配置","currentPeriodStars":142,"language":"Batchfile","languageColor":"#C1F12E","stargazers_count":204,"forks_count":0,"owner":{"avatar_url":"https://avatars.githubusercontent.com/u/31300706?s=40&v=4","login":"empty-233"},"buildBy":[{"avatar_url":"https://avatars.githubusercontent.com/u/31300706?s=40&v=4","login":"empty-233"},{"avatar_url":"https://avatars.githubusercontent.com/u/64016189?s=40&v=4","login":"kurisucat"},{"avatar_url":"https://avatars.githubusercontent.com/u/30508272?s=40&v=4","login":"eliozh"},{"avatar_url":"https://avatars.githubusercontent.com/u/37659729?s=40&v=4","login":"kongwu-empty"}]},{"full_name":"","description":"A script that gives you free RDP","currentPeriodStars":0,"language":"Batchfile","languageColor":"#C1F12E","stargazers_count":0,"forks_count":0,"owner":{},"buildBy":[]},{"full_name":"","description":"","currentPeriodStars":0,"stargazers_count":0,"forks_count":0,"owner":{},"buildBy":[]},{"full_name":"","description":"","currentPeriodStars":0,"stargazers_count":0,"forks_count":0,"owner":{},"buildBy":[]},{"full_name":"","description":"Repo for packaged Northstar releases","currentPeriodStars":6,"language":"Batchfile","languageColor":"#C1F12E","stargazers_count":1653,"forks_count":0,"owner":{"avatar_url":"https://avatars.githubusercontent.com/u/16687318?s=40&v=4","login":"abarichello"},"buildBy":[{"avatar_url":"https://avatars.githubusercontent.com/u/16687318?s=40&v=4","login":"abarichello"},{"avatar_url":"https://avatars.githubusercontent.com/u/40122905?s=40&v=4","login":"GeckoEidechse"},{"avatar_url":"https://avatars.githubusercontent.com/u/96569817?s=40&v=4","login":"pg9182"},{"avatar_url":"https://avatars.githubusercontent.com/u/11993538?s=40&v=4","login":"Alystrasz"},{"avatar_url":"https://avatars.githubusercontent.com/u/32057864?s=40&v=4","login":"BobTheBob9"}]},{"full_name":"","description":"Laboratoire virtuel via RDP","currentPeriodStars":0,"language":"Batchfile","languageColor":"#C1F12E","stargazers_count":5,"forks_count":0,"owner":{"avatar_url":"https://avatars.githubusercontent.com/u/36932970?s=40&v=4","login":"arnauddalayer"},"buildBy":[{"avatar_url":"https://avatars.githubusercontent.com/u/36932970?s=40&v=4","login":"arnauddalayer"}]},{"full_name":"","description":"","currentPeriodStars":0,"stargazers_count":0,"forks_count":0,"owner":{},"buildBy":[]},{"full_name":"","description":"","currentPeriodStars":0,"stargazers_count":0,"forks_count":0,"owner":{},"buildBy":[]},{"full_name":"","description":"Tron","currentPeriodStars":14,"language":"Batchfile","languageColor":"#C1F12E","stargazers_count":4103,"forks_count":0,"owner":{"avatar_url":"https://avatars.githubusercontent.com/u/5703764?s=40&v=4","login":"vocatus"},"buildBy":[{"avatar_url":"https://avatars.githubusercontent.com/u/5703764?s=40&v=4","login":"vocatus"},{"avatar_url":"https://avatars.githubusercontent.com/u/725456?s=40&v=4","login":"nemchik"},{"avatar_url":"https://avatars.githubusercontent.com/u/25354429?s=40&v=4","login":"madbomb122"},{"avatar_url":"https://avatars.githubusercontent.com/u/1191271?s=40&v=4","login":"RedBaron2"},{"avatar_url":"https://avatars.githubusercontent.com/u/4523551?s=40&v=4","login":"Kezxo"}]},{"full_name":"","description":"Desktop MOD (ad free)","currentPeriodStars":2,"language":"Batchfile","languageColor":"#C1F12E","stargazers_count":41,"forks_count":0,"owner":{"avatar_url":"https://avatars.githubusercontent.com/u/56351738?s=40&v=4","login":"ahtihska"},"buildBy":[{"avatar_url":"https://avatars.githubusercontent.com/u/56351738?s=40&v=4","login":"ahtihska"}]},{"full_name":"","description":"🌎 Windows 11 Settings, Tweaks, Scripts","currentPeriodStars":22,"language":"Batchfile","languageColor":"#C1F12E","stargazers_count":976,"forks_count":0,"owner":{"avatar_url":"https://avatars.githubusercontent.com/u/86190960?s=40&v=4","login":"awesome-windows11"},"buildBy":[{"avatar_url":"https://avatars.githubusercontent.com/u/86190960?s=40&v=4","login":"awesome-windows11"},{"avatar_url":"https://avatars.githubusercontent.com/u/87380272?s=40&v=4","login":"jestxfot"},{"avatar_url":"https://avatars.githubusercontent.com/u/4609678?s=40&v=4","login":"HUMENTH"},{"avatar_url":"https://avatars.githubusercontent.com/u/4913771?s=40&v=4","login":"simeononsecurity"}]},{"full_name":"","description":"A modern cross-platform low-level graphics library and rendering framework","currentPeriodStars":11,"language":"Batchfile","languageColor":"#C1F12E","stargazers_count":2913,"forks_count":0,"owner":{"avatar_url":"https://avatars.githubusercontent.com/u/61806567?s=40&v=4","login":"TheMostDiligent"},"buildBy":[{"avatar_url":"https://avatars.githubusercontent.com/u/61806567?s=40&v=4","login":"TheMostDiligent"},{"avatar_url":"https://avatars.githubusercontent.com/u/15135271?s=40&v=4","login":"DiligentGraphics"},{"avatar_url":"https://avatars.githubusercontent.com/u/2104977?s=40&v=4","login":"azhirnov"},{"avatar_url":"https://avatars.githubusercontent.com/u/25492259?s=40&v=4","login":"MikhailGorobets"},{"avatar_url":"https://avatars.githubusercontent.com/u/31071122?s=40&v=4","login":"dolphineye"}]},{"full_name":"","description":"A small Application for Windows that allows you to install the latest Version of ADB and Fastboot Files on the Computer without installing the entire Android SDK Package + Toolkit & Commands","currentPeriodStars":2,"language":"Batchfile","languageColor":"#C1F12E","stargazers_count":264,"forks_count":0,"owner":{"avatar_url":"https://avatars.githubusercontent.com/u/31441182?s=40&v=4","login":"K3V1991"},"buildBy":[{"avatar_url":"https://avatars.githubusercontent.com/u/31441182?s=40&v=4","login":"K3V1991"}]},{"full_name":"","description":"","currentPeriodStars":0,"stargazers_count":0,"forks_count":0,"owner":{},"buildBy":[]}]}