{"updateTime":"2025-08-10 02:31:46","data":[{"full_name":"","description":"Iconic font aggregator, collection, & patcher. 3,600+ icons, 50+ patched fonts: Hack, Source Code Pro, more. Glyph collections: Font Awesome, Material Design Icons, Octicons, & more","currentPeriodStars":141,"language":"CSS","languageColor":"#663399","stargazers_count":59069,"forks_count":0,"owner":{"avatar_url":"https://avatars.githubusercontent.com/u/16012374?s=40&v=4","login":"Finii"},"buildBy":[{"avatar_url":"https://avatars.githubusercontent.com/u/16012374?s=40&v=4","login":"Finii"},{"avatar_url":"https://avatars.githubusercontent.com/u/8083459?s=40&v=4","login":"ryanoasis"},{"avatar_url":"https://avatars.githubusercontent.com/in/15368?s=40&v=4","login":"github-actions"},{"avatar_url":"https://avatars.githubusercontent.com/in/23186?s=40&v=4","login":"allcontributors"},{"avatar_url":"https://avatars.githubusercontent.com/u/4368882?s=40&v=4","login":"sharkusk"}]},{"full_name":"","description":"Open-source tool to build your Windows script from scratch. It includes debloat, privacy, performance & app installing scripts.","currentPeriodStars":52,"language":"CSS","languageColor":"#663399","stargazers_count":1502,"forks_count":0,"owner":{"avatar_url":"https://avatars.githubusercontent.com/u/137506210?s=40&v=4","login":"flick9000"},"buildBy":[{"avatar_url":"https://avatars.githubusercontent.com/u/137506210?s=40&v=4","login":"flick9000"},{"avatar_url":"https://avatars.githubusercontent.com/in/29110?s=40&v=4","login":"dependabot"},{"avatar_url":"https://avatars.githubusercontent.com/u/10416814?s=40&v=4","login":"Dobrowit"}]},{"full_name":"","description":"Accurately Locate Smartphones using Social Engineering","currentPeriodStars":40,"language":"CSS","languageColor":"#663399","stargazers_count":8304,"forks_count":0,"owner":{"avatar_url":"https://avatars.githubusercontent.com/u/36354846?s=40&v=4","login":"thewhiteh4t"},"buildBy":[{"avatar_url":"https://avatars.githubusercontent.com/u/36354846?s=40&v=4","login":"thewhiteh4t"},{"avatar_url":"https://avatars.githubusercontent.com/u/11071770?s=40&v=4","login":"Resousse"},{"avatar_url":"https://avatars.githubusercontent.com/u/89315818?s=40&v=4","login":"a7maadf"},{"avatar_url":"https://avatars.githubusercontent.com/u/32103950?s=40&v=4","login":"MasterDevX"},{"avatar_url":"https://avatars.githubusercontent.com/u/30162978?s=40&v=4","login":"thehappydinoa"}]},{"full_name":"","description":"A theme for obsidian.md","currentPeriodStars":20,"language":"CSS","languageColor":"#663399","stargazers_count":1919,"forks_count":0,"owner":{"avatar_url":"https://avatars.githubusercontent.com/u/23567154?s=40&v=4","login":"Akifyss"},"buildBy":[{"avatar_url":"https://avatars.githubusercontent.com/u/23567154?s=40&v=4","login":"Akifyss"},{"avatar_url":"https://avatars.githubusercontent.com/u/23419678?s=40&v=4","login":"velviagris"},{"avatar_url":"https://avatars.githubusercontent.com/u/93238080?s=40&v=4","login":"ProudBenzene"},{"avatar_url":"https://avatars.githubusercontent.com/u/8663074?s=40&v=4","login":"chasemccoy"},{"avatar_url":"https://avatars.githubusercontent.com/u/62891170?s=40&v=4","login":"4rtamis"}]},{"full_name":"","description":"A distraction-free and highly customizable theme for Obsidian.","currentPeriodStars":19,"language":"CSS","languageColor":"#663399","stargazers_count":4256,"forks_count":0,"owner":{"avatar_url":"https://avatars.githubusercontent.com/u/10565871?s=40&v=4","login":"kepano"},"buildBy":[{"avatar_url":"https://avatars.githubusercontent.com/u/10565871?s=40&v=4","login":"kepano"},{"avatar_url":"https://avatars.githubusercontent.com/u/693981?s=40&v=4","login":"liamcain"},{"avatar_url":"https://avatars.githubusercontent.com/u/59741989?s=40&v=4","login":"phibr0"},{"avatar_url":"https://avatars.githubusercontent.com/u/60461730?s=40&v=4","login":"isunjn"},{"avatar_url":"https://avatars.githubusercontent.com/u/177491?s=40&v=4","login":"trashhalo"}]},{"full_name":"","description":"","currentPeriodStars":0,"stargazers_count":0,"forks_count":0,"owner":{},"buildBy":[]},{"full_name":"","description":"Вопросы для подготовки к интервью на позицию Python Developer","currentPeriodStars":13,"language":"CSS","languageColor":"#663399","stargazers_count":2144,"forks_count":0,"owner":{"avatar_url":"https://avatars.githubusercontent.com/u/28621349?s=40&v=4","login":"yakimka"},"buildBy":[{"avatar_url":"https://avatars.githubusercontent.com/u/28621349?s=40&v=4","login":"yakimka"},{"avatar_url":"https://avatars.githubusercontent.com/u/22882593?s=40&v=4","login":"pavlenk0"},{"avatar_url":"https://avatars.githubusercontent.com/in/2740?s=40&v=4","login":"renovate"},{"avatar_url":"https://avatars.githubusercontent.com/u/26921504?s=40&v=4","login":"TrueTony"},{"avatar_url":"https://avatars.githubusercontent.com/u/43515791?s=40&v=4","login":"warmsnow17"}]},{"full_name":"","description":"Documentation for GX mods","currentPeriodStars":1,"language":"CSS","languageColor":"#663399","stargazers_count":867,"forks_count":0,"owner":{"avatar_url":"https://avatars.githubusercontent.com/u/124875542?s=40&v=4","login":"themaciekk"},"buildBy":[{"avatar_url":"https://avatars.githubusercontent.com/u/124875542?s=40&v=4","login":"themaciekk"},{"avatar_url":"https://avatars.githubusercontent.com/u/21360237?s=40&v=4","login":"gurpreetsinghmatharoo"},{"avatar_url":"https://avatars.githubusercontent.com/u/950537?s=40&v=4","login":"emoller"},{"avatar_url":"https://avatars.githubusercontent.com/u/20278113?s=40&v=4","login":"opera-borist"},{"avatar_url":"https://avatars.githubusercontent.com/u/79467907?s=40&v=4","login":"astrum-nova"}]},{"full_name":"","description":"🍿 A cross-browser library of CSS animations. As easy to use as an easy thing.","currentPeriodStars":33,"language":"CSS","languageColor":"#663399","stargazers_count":82021,"forks_count":0,"owner":{"avatar_url":"https://avatars.githubusercontent.com/u/439365?s=40&v=4","login":"daneden"},"buildBy":[{"avatar_url":"https://avatars.githubusercontent.com/u/439365?s=40&v=4","login":"daneden"},{"avatar_url":"https://avatars.githubusercontent.com/in/29110?s=40&v=4","login":"dependabot"},{"avatar_url":"https://avatars.githubusercontent.com/u/5007208?s=40&v=4","login":"eltonmesquita"},{"avatar_url":"https://avatars.githubusercontent.com/u/75607?s=40&v=4","login":"suissa"},{"avatar_url":"https://avatars.githubusercontent.com/u/15052701?s=40&v=4","login":"warengonzaga"}]},{"full_name":"","description":"Personal theme for Obsidian","currentPeriodStars":19,"language":"CSS","languageColor":"#663399","stargazers_count":2749,"forks_count":0,"owner":{"avatar_url":"https://avatars.githubusercontent.com/u/102488279?s=40&v=4","login":"AnubisNekhet"},"buildBy":[{"avatar_url":"https://avatars.githubusercontent.com/u/102488279?s=40&v=4","login":"AnubisNekhet"},{"avatar_url":"https://avatars.githubusercontent.com/u/134939?s=40&v=4","login":"pryley"},{"avatar_url":"https://avatars.githubusercontent.com/u/97590612?s=40&v=4","login":"notnotnescap"},{"avatar_url":"https://avatars.githubusercontent.com/u/19956672?s=40&v=4","login":"iwa"},{"avatar_url":"https://avatars.githubusercontent.com/u/8266075?s=40&v=4","login":"DIYgod"}]},{"full_name":"","description":"Carefully Designed Icon Library. MingCute is a set of simple and exquisite open-source icon library. Whether you're a designer or a developer, it's perfect for use in web and mobile.","currentPeriodStars":31,"language":"CSS","languageColor":"#663399","stargazers_count":1109,"forks_count":0,"owner":{"avatar_url":"https://avatars.githubusercontent.com/u/86995908?s=40&v=4","login":"Richard9394"},"buildBy":[{"avatar_url":"https://avatars.githubusercontent.com/u/86995908?s=40&v=4","login":"Richard9394"},{"avatar_url":"https://avatars.githubusercontent.com/u/81922999?s=40&v=4","login":"Barry-Flynn"},{"avatar_url":"https://avatars.githubusercontent.com/u/102006756?s=40&v=4","login":"ZigaoWang"}]}]}