{"updateTime":"2023-10-31 02:20:22","data":[{"full_name":"","description":"The Nearest Regularized Subspace Classifier","currentPeriodStars":0,"language":"MATLAB","languageColor":"#e16737","stargazers_count":2,"forks_count":0,"owner":{"avatar_url":"https://avatars.githubusercontent.com/u/1223539?s=40&v=4","login":"eric-tramel"},"buildBy":[{"avatar_url":"https://avatars.githubusercontent.com/u/1223539?s=40&v=4","login":"eric-tramel"}]},{"full_name":"","description":"Present a recognition memory task with saccadic and manual responses via Matlab Psychtoolbox","currentPeriodStars":0,"language":"MATLAB","languageColor":"#e16737","stargazers_count":0,"forks_count":0,"owner":{"avatar_url":"https://avatars.githubusercontent.com/u/1580672?s=40&v=4","login":"amgordon"},"buildBy":[{"avatar_url":"https://avatars.githubusercontent.com/u/1580672?s=40&v=4","login":"amgordon"}]},{"full_name":"","description":"遗传算法、免疫算法、退火算法、粒子群算法、鱼群算法、蚁群算法和神经网络算法等常用智能算法的MATLAB实现","currentPeriodStars":2,"language":"MATLAB","languageColor":"#e16737","stargazers_count":272,"forks_count":0,"owner":{"avatar_url":"https://avatars.githubusercontent.com/u/34783005?s=40&v=4","login":"vonsylvia"},"buildBy":[{"avatar_url":"https://avatars.githubusercontent.com/u/34783005?s=40&v=4","login":"vonsylvia"}]},{"full_name":"","description":"Brainstorm software: MEG, EEG, fNIRS, ECoG, sEEG and electrophysiology","currentPeriodStars":2,"language":"MATLAB","languageColor":"#e16737","stargazers_count":326,"forks_count":0,"owner":{"avatar_url":"https://avatars.githubusercontent.com/u/6920058?s=40&v=4","login":"ftadel"},"buildBy":[{"avatar_url":"https://avatars.githubusercontent.com/u/6920058?s=40&v=4","login":"ftadel"},{"avatar_url":"https://avatars.githubusercontent.com/u/8238803?s=40&v=4","login":"rcassani"},{"avatar_url":"https://avatars.githubusercontent.com/u/23224563?s=40&v=4","login":"mpompolas"},{"avatar_url":"https://avatars.githubusercontent.com/u/31040756?s=40&v=4","login":"Moo-Marc"},{"avatar_url":"https://avatars.githubusercontent.com/u/24530402?s=40&v=4","login":"Edouard2laire"}]},{"full_name":"","description":"JSONLab: compact, portable, robust JSON/binary-JSON encoder/decoder for MATLAB/Octave","currentPeriodStars":1,"language":"MATLAB","languageColor":"#e16737","stargazers_count":288,"forks_count":0,"owner":{"avatar_url":"https://avatars.githubusercontent.com/u/226913?s=40&v=4","login":"fangq"},"buildBy":[{"avatar_url":"https://avatars.githubusercontent.com/u/226913?s=40&v=4","login":"fangq"},{"avatar_url":"https://avatars.githubusercontent.com/u/13461059?s=40&v=4","login":"astorfi"},{"avatar_url":"https://avatars.githubusercontent.com/u/3234522?s=40&v=4","login":"DimitriPapadopoulos"},{"avatar_url":"https://avatars.githubusercontent.com/u/21337619?s=40&v=4","login":"roslovets"},{"avatar_url":"https://avatars.githubusercontent.com/u/375685?s=40&v=4","login":"vrichter"}]},{"full_name":"","description":"A few animation/physics projects done in matlab.","currentPeriodStars":0,"language":"MATLAB","languageColor":"#e16737","stargazers_count":6,"forks_count":0,"owner":{"avatar_url":"https://avatars.githubusercontent.com/u/1954057?s=40&v=4","login":"rggeorge"},"buildBy":[{"avatar_url":"https://avatars.githubusercontent.com/u/1954057?s=40&v=4","login":"rggeorge"}]},{"full_name":"","description":"","currentPeriodStars":0,"stargazers_count":0,"forks_count":0,"owner":{},"buildBy":[]},{"full_name":"","description":"The replication data and files for Liangjun Su, Zhentao Shi and Peter Phillips (2016, Econometrica): “Identifying Latent Structures in Panel Data”","currentPeriodStars":0,"language":"MATLAB","languageColor":"#e16737","stargazers_count":19,"forks_count":0,"owner":{"avatar_url":"https://avatars.githubusercontent.com/u/818353?s=40&v=4","login":"zhentaoshi"},"buildBy":[{"avatar_url":"https://avatars.githubusercontent.com/u/818353?s=40&v=4","login":"zhentaoshi"}]},{"full_name":"","description":"Matlab code of machine learning algorithms in book PRML","currentPeriodStars":5,"language":"MATLAB","languageColor":"#e16737","stargazers_count":5888,"forks_count":0,"owner":{"avatar_url":"https://avatars.githubusercontent.com/u/1963308?s=40&v=4","login":"sth4nth"},"buildBy":[{"avatar_url":"https://avatars.githubusercontent.com/u/1963308?s=40&v=4","login":"sth4nth"},{"avatar_url":"https://avatars.githubusercontent.com/u/2232328?s=40&v=4","login":"weilinear"},{"avatar_url":"https://avatars.githubusercontent.com/u/7910665?s=40&v=4","login":"cheerconi"}]},{"full_name":"","description":"Deep Learning-based Image Fusion: A Survey","currentPeriodStars":10,"language":"MATLAB","languageColor":"#e16737","stargazers_count":470,"forks_count":0,"owner":{"avatar_url":"https://avatars.githubusercontent.com/u/59408033?s=40&v=4","login":"Linfeng-Tang"},"buildBy":[{"avatar_url":"https://avatars.githubusercontent.com/u/59408033?s=40&v=4","login":"Linfeng-Tang"}]},{"full_name":"","description":"EKF IMU Fusion Algorithms","currentPeriodStars":1,"language":"MATLAB","languageColor":"#e16737","stargazers_count":158,"forks_count":0,"owner":{"avatar_url":"https://avatars.githubusercontent.com/u/16507097?s=40&v=4","login":"meyiao"},"buildBy":[{"avatar_url":"https://avatars.githubusercontent.com/u/16507097?s=40&v=4","login":"meyiao"}]},{"full_name":"","description":"The MATLAB toolbox for MEG, EEG and iEEG analysis","currentPeriodStars":4,"language":"MATLAB","languageColor":"#e16737","stargazers_count":760,"forks_count":0,"owner":{"avatar_url":"https://avatars.githubusercontent.com/u/899043?s=40&v=4","login":"robertoostenveld"},"buildBy":[{"avatar_url":"https://avatars.githubusercontent.com/u/899043?s=40&v=4","login":"robertoostenveld"},{"avatar_url":"https://avatars.githubusercontent.com/u/1517611?s=40&v=4","login":"schoffelen"},{"avatar_url":"https://avatars.githubusercontent.com/u/3042751?s=40&v=4","login":"Spaak"},{"avatar_url":"https://avatars.githubusercontent.com/u/1453927?s=40&v=4","login":"nno"},{"avatar_url":"https://avatars.githubusercontent.com/u/3984917?s=40&v=4","login":"StolkArjen"}]},{"full_name":"","description":"OpenFace – a state-of-the art tool intended for facial landmark detection, head pose estimation, facial action unit recognition, and eye-gaze estimation.","currentPeriodStars":10,"language":"MATLAB","languageColor":"#e16737","stargazers_count":6233,"forks_count":0,"owner":{"avatar_url":"https://avatars.githubusercontent.com/u/7542364?s=40&v=4","login":"TadasBaltrusaitis"},"buildBy":[{"avatar_url":"https://avatars.githubusercontent.com/u/7542364?s=40&v=4","login":"TadasBaltrusaitis"},{"avatar_url":"https://avatars.githubusercontent.com/u/1742611?s=40&v=4","login":"simonmssu"},{"avatar_url":"https://avatars.githubusercontent.com/u/3036816?s=40&v=4","login":"fxfactorial"},{"avatar_url":"https://avatars.githubusercontent.com/u/8654460?s=40&v=4","login":"dshahrokhian"},{"avatar_url":"https://avatars.githubusercontent.com/u/1950941?s=40&v=4","login":"chiragraman"}]},{"full_name":"","description":"EEGLAB is an open source signal processing environment for electrophysiological signals running on Matlab and developed at the SCCN/UCSD","currentPeriodStars":2,"language":"MATLAB","languageColor":"#e16737","stargazers_count":485,"forks_count":0,"owner":{"avatar_url":"https://avatars.githubusercontent.com/u/1872705?s=40&v=4","login":"arnodelorme"},"buildBy":[{"avatar_url":"https://avatars.githubusercontent.com/u/1872705?s=40&v=4","login":"arnodelorme"},{"avatar_url":"https://avatars.githubusercontent.com/u/5943254?s=40&v=4","login":"nucleuscub"},{"avatar_url":"https://avatars.githubusercontent.com/u/774851?s=40&v=4","login":"tfernsle"},{"avatar_url":"https://avatars.githubusercontent.com/u/4206824?s=40&v=4","login":"bigdelys"},{"avatar_url":"https://avatars.githubusercontent.com/u/4772878?s=40&v=4","login":"CPernet"}]}]}