{"updateTime":"2023-03-09 02:24:33","data":[{"full_name":"material-components/material-web","description":"Material Design Web Components","currentPeriodStars":77,"language":"SCSS","languageColor":"#c6538c","stargazers_count":5203,"forks_count":0,"owner":{"avatar_url":"https://avatars.githubusercontent.com/u/5981958?s=40&v=4","login":"e111077"},"buildBy":[{"avatar_url":"https://avatars.githubusercontent.com/u/5981958?s=40&v=4","login":"e111077"},{"avatar_url":"https://avatars.githubusercontent.com/u/34382620?s=40&v=4","login":"asyncLiz"},{"avatar_url":"https://avatars.githubusercontent.com/u/46725?s=40&v=4","login":"dfreedm"},{"avatar_url":"https://avatars.githubusercontent.com/in/44061?s=40&v=4","login":"copybara-service"},{"avatar_url":"https://avatars.githubusercontent.com/u/15639815?s=40&v=4","login":"tedium-bot"}]},{"full_name":"keyvanakbary/learning-notes","description":"Notes on books I read, talks I watch, articles I study, and papers I love","currentPeriodStars":30,"language":"SCSS","languageColor":"#c6538c","stargazers_count":3117,"forks_count":0,"owner":{"avatar_url":"https://avatars.githubusercontent.com/u/717129?s=40&v=4","login":"keyvanakbary"},"buildBy":[{"avatar_url":"https://avatars.githubusercontent.com/u/717129?s=40&v=4","login":"keyvanakbary"},{"avatar_url":"https://avatars.githubusercontent.com/u/2096101?s=40&v=4","login":"Kikobeats"},{"avatar_url":"https://avatars.githubusercontent.com/u/477525?s=40&v=4","login":"can-z"}]},{"full_name":"prakhar1989/docker-curriculum","description":"🐬 A comprehensive tutorial on getting started with Docker!","currentPeriodStars":16,"language":"SCSS","languageColor":"#c6538c","stargazers_count":5038,"forks_count":0,"owner":{"avatar_url":"https://avatars.githubusercontent.com/u/649249?s=40&v=4","login":"prakhar1989"},"buildBy":[{"avatar_url":"https://avatars.githubusercontent.com/u/649249?s=40&v=4","login":"prakhar1989"},{"avatar_url":"https://avatars.githubusercontent.com/u/2433509?s=40&v=4","login":"schlosser"},{"avatar_url":"https://avatars.githubusercontent.com/u/6964693?s=40&v=4","login":"robertoej"},{"avatar_url":"https://avatars.githubusercontent.com/in/29110?s=40&v=4","login":"dependabot"},{"avatar_url":"https://avatars.githubusercontent.com/u/9309145?s=40&v=4","login":"camisatx"}]},{"full_name":"slatedocs/slate","description":"Beautiful static documentation for your API","currentPeriodStars":26,"language":"SCSS","languageColor":"#c6538c","stargazers_count":35007,"forks_count":0,"owner":{"avatar_url":"https://avatars.githubusercontent.com/u/1976330?s=40&v=4","login":"lord"},"buildBy":[{"avatar_url":"https://avatars.githubusercontent.com/u/1976330?s=40&v=4","login":"lord"},{"avatar_url":"https://avatars.githubusercontent.com/u/1845314?s=40&v=4","login":"MasterOdin"},{"avatar_url":"https://avatars.githubusercontent.com/in/29110?s=40&v=4","login":"dependabot"},{"avatar_url":"https://avatars.githubusercontent.com/in/2141?s=40&v=4","login":"dependabot-preview"},{"avatar_url":"https://avatars.githubusercontent.com/u/569270?s=40&v=4","login":"chrissrogers"}]},{"full_name":"Dorota1997/react-frontend-dev-portfolio","description":"Easy to adapt and deploy React portfolio inspired with solutions found at GitHub.","currentPeriodStars":10,"language":"SCSS","languageColor":"#c6538c","stargazers_count":693,"forks_count":0,"owner":{"avatar_url":"https://avatars.githubusercontent.com/u/25982919?s=40&v=4","login":"trolit"},"buildBy":[{"avatar_url":"https://avatars.githubusercontent.com/u/25982919?s=40&v=4","login":"trolit"},{"avatar_url":"https://avatars.githubusercontent.com/u/25982852?s=40&v=4","login":"Dorota1997"},{"avatar_url":"https://avatars.githubusercontent.com/u/525557?s=40&v=4","login":"igorperic17"},{"avatar_url":"https://avatars.githubusercontent.com/u/4896595?s=40&v=4","login":"mangelarilla"},{"avatar_url":"https://avatars.githubusercontent.com/u/11299099?s=40&v=4","login":"DavidMatalik"}]},{"full_name":"primer/css","description":"The CSS design system that powers GitHub","currentPeriodStars":28,"language":"SCSS","languageColor":"#c6538c","stargazers_count":11885,"forks_count":0,"owner":{"avatar_url":"https://avatars.githubusercontent.com/u/113896?s=40&v=4","login":"shawnbot"},"buildBy":[{"avatar_url":"https://avatars.githubusercontent.com/u/113896?s=40&v=4","login":"shawnbot"},{"avatar_url":"https://avatars.githubusercontent.com/u/54012?s=40&v=4","login":"jonrohan"},{"avatar_url":"https://avatars.githubusercontent.com/u/378023?s=40&v=4","login":"simurai"},{"avatar_url":"https://avatars.githubusercontent.com/in/29110?s=40&v=4","login":"dependabot"},{"avatar_url":"https://avatars.githubusercontent.com/u/334891?s=40&v=4","login":"broccolini"}]},{"full_name":"creativetimofficial/material-dashboard","description":"Material Dashboard - Open Source Bootstrap 5 Material Design Admin","currentPeriodStars":8,"language":"SCSS","languageColor":"#c6538c","stargazers_count":10455,"forks_count":0,"owner":{"avatar_url":"https://avatars.githubusercontent.com/u/17456857?s=40&v=4","login":"dragosct"},"buildBy":[{"avatar_url":"https://avatars.githubusercontent.com/u/17456857?s=40&v=4","login":"dragosct"},{"avatar_url":"https://avatars.githubusercontent.com/u/2517758?s=40&v=4","login":"alexandru-paduraru"},{"avatar_url":"https://avatars.githubusercontent.com/u/21063398?s=40&v=4","login":"groovemen"},{"avatar_url":"https://avatars.githubusercontent.com/u/4600172?s=40&v=4","login":"marqbeniamin"},{"avatar_url":"https://avatars.githubusercontent.com/u/2582303?s=40&v=4","login":"conacelelena"}]},{"full_name":"mdbootstrap/mdb-ui-kit","description":"Bootstrap 5 & Material Design 2.0 UI KIT","currentPeriodStars":29,"language":"SCSS","languageColor":"#c6538c","stargazers_count":23119,"forks_count":0,"owner":{"avatar_url":"https://avatars.githubusercontent.com/u/136564?s=40&v=4","login":"rosskevin"},"buildBy":[{"avatar_url":"https://avatars.githubusercontent.com/u/136564?s=40&v=4","login":"rosskevin"},{"avatar_url":"https://avatars.githubusercontent.com/u/5382443?s=40&v=4","login":"FezVrasta"},{"avatar_url":"https://avatars.githubusercontent.com/u/994964?s=40&v=4","login":"GradyD"},{"avatar_url":"https://avatars.githubusercontent.com/u/1546207?s=40&v=4","login":"nelsonomuto"},{"avatar_url":"https://avatars.githubusercontent.com/u/5188806?s=40&v=4","login":"npvn"}]},{"full_name":"dxp10/mysite","description":"","currentPeriodStars":0,"stargazers_count":0,"forks_count":0,"owner":{},"buildBy":[]},{"full_name":"mate-academy/layout_miami","description":"","currentPeriodStars":0,"stargazers_count":0,"forks_count":0,"owner":{},"buildBy":[]},{"full_name":"edx/brand-edx.org","description":"","currentPeriodStars":0,"stargazers_count":0,"forks_count":0,"owner":{},"buildBy":[]},{"full_name":"ClearVision/ClearVision-v6","description":"Highly customizable theme for BetterDiscord.","currentPeriodStars":3,"language":"SCSS","languageColor":"#c6538c","stargazers_count":270,"forks_count":0,"owner":{"avatar_url":"https://avatars.githubusercontent.com/u/19844016?s=40&v=4","login":"Zerthox"},"buildBy":[{"avatar_url":"https://avatars.githubusercontent.com/u/19844016?s=40&v=4","login":"Zerthox"},{"avatar_url":"https://avatars.githubusercontent.com/u/26217384?s=40&v=4","login":"Leozard"},{"avatar_url":"https://avatars.githubusercontent.com/u/58749666?s=40&v=4","login":"NyxIsBad"},{"avatar_url":"https://avatars.githubusercontent.com/u/54205089?s=40&v=4","login":"Mentalscars"},{"avatar_url":"https://avatars.githubusercontent.com/u/7635652?s=40&v=4","login":"untuned"}]},{"full_name":"mate-academy/Kickstarter","description":"","currentPeriodStars":0,"stargazers_count":0,"forks_count":0,"owner":{},"buildBy":[]},{"full_name":"adeo/lmru--tech","description":"Leroy Merlin Tech","currentPeriodStars":0,"language":"SCSS","languageColor":"#c6538c","stargazers_count":25,"forks_count":0,"owner":{"avatar_url":"https://avatars.githubusercontent.com/u/9394918?s=40&v=4","login":"voborgus"},"buildBy":[{"avatar_url":"https://avatars.githubusercontent.com/u/9394918?s=40&v=4","login":"voborgus"},{"avatar_url":"https://avatars.githubusercontent.com/u/44237536?s=40&v=4","login":"alem355"},{"avatar_url":"https://avatars.githubusercontent.com/u/66905852?s=40&v=4","login":"chylman"},{"avatar_url":"https://avatars.githubusercontent.com/u/60796974?s=40&v=4","login":"arkartavtsev-liga"},{"avatar_url":"https://avatars.githubusercontent.com/u/47631138?s=40&v=4","login":"ValeryLaptev"}]},{"full_name":"miniMAC/magic","description":"CSS3 Animations with special effects","currentPeriodStars":20,"language":"SCSS","languageColor":"#c6538c","stargazers_count":7958,"forks_count":0,"owner":{"avatar_url":"https://avatars.githubusercontent.com/u/1235741?s=40&v=4","login":"miniMAC"},"buildBy":[{"avatar_url":"https://avatars.githubusercontent.com/u/1235741?s=40&v=4","login":"miniMAC"},{"avatar_url":"https://avatars.githubusercontent.com/u/10754058?s=40&v=4","login":"Sylvenas"},{"avatar_url":"https://avatars.githubusercontent.com/u/609761?s=40&v=4","login":"jrutheiser"},{"avatar_url":"https://avatars.githubusercontent.com/u/1639813?s=40&v=4","login":"skeiter9"},{"avatar_url":"https://avatars.githubusercontent.com/u/421861?s=40&v=4","login":"hainuo"}]},{"full_name":"mate-academy/layout_creativeBakery","description":"","currentPeriodStars":0,"stargazers_count":0,"forks_count":0,"owner":{},"buildBy":[]},{"full_name":"sass/sass-spec","description":"Official Sass Spec Suite","currentPeriodStars":0,"language":"SCSS","languageColor":"#c6538c","stargazers_count":186,"forks_count":0,"owner":{"avatar_url":"https://avatars.githubusercontent.com/u/579928?s=40&v=4","login":"xzyfer"},"buildBy":[{"avatar_url":"https://avatars.githubusercontent.com/u/579928?s=40&v=4","login":"xzyfer"},{"avatar_url":"https://avatars.githubusercontent.com/u/188?s=40&v=4","login":"nex3"},{"avatar_url":"https://avatars.githubusercontent.com/u/282293?s=40&v=4","login":"mgreter"},{"avatar_url":"https://avatars.githubusercontent.com/u/1839?s=40&v=4","login":"chriseppstein"},{"avatar_url":"https://avatars.githubusercontent.com/u/439401?s=40&v=4","login":"stof"}]},{"full_name":"edx/ux-pattern-library","description":"The (working) Visual, UI, and Front End Styleguide for edX.","currentPeriodStars":2,"language":"SCSS","languageColor":"#c6538c","stargazers_count":279,"forks_count":0,"owner":{"avatar_url":"https://avatars.githubusercontent.com/u/163763?s=40&v=4","login":"talbs"},"buildBy":[{"avatar_url":"https://avatars.githubusercontent.com/u/163763?s=40&v=4","login":"talbs"},{"avatar_url":"https://avatars.githubusercontent.com/u/5985072?s=40&v=4","login":"andy-armstrong"},{"avatar_url":"https://avatars.githubusercontent.com/u/2112024?s=40&v=4","login":"downzer0"},{"avatar_url":"https://avatars.githubusercontent.com/u/407639?s=40&v=4","login":"bjacobel"},{"avatar_url":"https://avatars.githubusercontent.com/u/5265058?s=40&v=4","login":"dsjen"}]},{"full_name":"ViktorSvertoka/ice-cream","description":"Website ice cream, team project on html and css course🍦","currentPeriodStars":15,"language":"SCSS","languageColor":"#c6538c","stargazers_count":64,"forks_count":0,"owner":{"avatar_url":"https://avatars.githubusercontent.com/u/115661003?s=40&v=4","login":"ViktorSvertoka"},"buildBy":[{"avatar_url":"https://avatars.githubusercontent.com/u/115661003?s=40&v=4","login":"ViktorSvertoka"},{"avatar_url":"https://avatars.githubusercontent.com/u/17479434?s=40&v=4","login":"luxplanjay"},{"avatar_url":"https://avatars.githubusercontent.com/u/29813098?s=40&v=4","login":"baschenko"},{"avatar_url":"https://avatars.githubusercontent.com/u/115738100?s=40&v=4","login":"samusdimitriy"},{"avatar_url":"https://avatars.githubusercontent.com/u/116813260?s=40&v=4","login":"Sergiy-Yevchihen"}]},{"full_name":"brianmaierjr/long-haul","description":"A minimal, type-focused Jekyll theme.","currentPeriodStars":1,"language":"SCSS","languageColor":"#c6538c","stargazers_count":606,"forks_count":0,"owner":{"avatar_url":"https://avatars.githubusercontent.com/u/2747377?s=40&v=4","login":"brianmaierjr"},"buildBy":[{"avatar_url":"https://avatars.githubusercontent.com/u/2747377?s=40&v=4","login":"brianmaierjr"},{"avatar_url":"https://avatars.githubusercontent.com/in/29110?s=40&v=4","login":"dependabot"},{"avatar_url":"https://avatars.githubusercontent.com/u/28616?s=40&v=4","login":"Arcnor"},{"avatar_url":"https://avatars.githubusercontent.com/u/15349868?s=40&v=4","login":"ggio"},{"avatar_url":"https://avatars.githubusercontent.com/u/135808?s=40&v=4","login":"gonsie"}]},{"full_name":"ilyas-it83/CloudComparer","description":"Compare the various managed cloud services offered by the major public cloud providers in the market.","currentPeriodStars":10,"language":"SCSS","languageColor":"#c6538c","stargazers_count":1241,"forks_count":0,"owner":{"avatar_url":"https://avatars.githubusercontent.com/u/10421745?s=40&v=4","login":"ilyas-it83"},"buildBy":[{"avatar_url":"https://avatars.githubusercontent.com/u/10421745?s=40&v=4","login":"ilyas-it83"},{"avatar_url":"https://avatars.githubusercontent.com/u/8345686?s=40&v=4","login":"owhc"},{"avatar_url":"https://avatars.githubusercontent.com/u/21144140?s=40&v=4","login":"GuruCharan94"},{"avatar_url":"https://avatars.githubusercontent.com/u/6552440?s=40&v=4","login":"VidyasagarMSC"},{"avatar_url":"https://avatars.githubusercontent.com/u/24225497?s=40&v=4","login":"odykyi"}]},{"full_name":"creativetimofficial/paper-kit-2-angular","description":"Free Bootstrap 4 UI Kit for Angular 2+","currentPeriodStars":0,"language":"SCSS","languageColor":"#c6538c","stargazers_count":152,"forks_count":0,"owner":{"avatar_url":"https://avatars.githubusercontent.com/u/22840626?s=40&v=4","login":"chelaruc"},"buildBy":[{"avatar_url":"https://avatars.githubusercontent.com/u/22840626?s=40&v=4","login":"chelaruc"},{"avatar_url":"https://avatars.githubusercontent.com/u/27827318?s=40&v=4","login":"rarestoma"},{"avatar_url":"https://avatars.githubusercontent.com/u/4600172?s=40&v=4","login":"marqbeniamin"},{"avatar_url":"https://avatars.githubusercontent.com/u/2517758?s=40&v=4","login":"alexandru-paduraru"},{"avatar_url":"https://avatars.githubusercontent.com/u/60063724?s=40&v=4","login":"taqishah1214"}]},{"full_name":"maildev/maildev","description":"📫 SMTP Server + Web Interface for viewing and testing emails during development.","currentPeriodStars":15,"language":"SCSS","languageColor":"#c6538c","stargazers_count":3865,"forks_count":0,"owner":{"avatar_url":"https://avatars.githubusercontent.com/u/1509457?s=40&v=4","login":"djfarrelly"},"buildBy":[{"avatar_url":"https://avatars.githubusercontent.com/u/1509457?s=40&v=4","login":"djfarrelly"},{"avatar_url":"https://avatars.githubusercontent.com/u/7447244?s=40&v=4","login":"DominikSerafin"},{"avatar_url":"https://avatars.githubusercontent.com/u/1500781?s=40&v=4","login":"soulteary"},{"avatar_url":"https://avatars.githubusercontent.com/u/2752200?s=40&v=4","login":"oktapodia"},{"avatar_url":"https://avatars.githubusercontent.com/u/1391577?s=40&v=4","login":"donut87"}]},{"full_name":"creativetimofficial/argon-design-system-angular","description":"","currentPeriodStars":0,"stargazers_count":0,"forks_count":0,"owner":{},"buildBy":[]},{"full_name":"wowchemy/wowchemy-hugo-themes","description":"🔥 Hugo website builder, Hugo themes & Hugo CMS. No code, easily build with blocks! 创建在线课程，学术简历或初创网站。#OpenScience","currentPeriodStars":23,"language":"SCSS","languageColor":"#c6538c","stargazers_count":7048,"forks_count":0,"owner":{"avatar_url":"https://avatars.githubusercontent.com/u/7537639?s=40&v=4","login":"gcushen"},"buildBy":[{"avatar_url":"https://avatars.githubusercontent.com/u/7537639?s=40&v=4","login":"gcushen"},{"avatar_url":"https://avatars.githubusercontent.com/u/2152937?s=40&v=4","login":"rhewett"},{"avatar_url":"https://avatars.githubusercontent.com/u/3974108?s=40&v=4","login":"seisman"},{"avatar_url":"https://avatars.githubusercontent.com/u/75446?s=40&v=4","login":"jpawlowski"},{"avatar_url":"https://avatars.githubusercontent.com/u/1327215?s=40&v=4","login":"kulla"}]}]}